student_esm/__init__.py
student_esm/data/student_ESM.csv
student_esm-1.0.dist-info/METADATA
student_esm-1.0.dist-info/WHEEL
student_esm-1.0.dist-info/top_level.txt
student_esm-1.0.dist-info/RECORD
