Metadata-Version: 2.1
Name: student-esm
Version: 1.0
Summary: Package containing student ESM data from the Michigan State RLDL Lab, 2024.
Requires-Dist: pandas
